numops/__init__.py
numops/basic.py
numops-0.0.7.dist-info/LICENSE
numops-0.0.7.dist-info/METADATA
numops-0.0.7.dist-info/WHEEL
numops-0.0.7.dist-info/top_level.txt
numops-0.0.7.dist-info/RECORD
