Metadata-Version: 2.1
Name: numops
Version: 0.0.7
Summary: UNKNOWN
Home-page: https://github.com/vivekkya/auto-release-to-pypi.git
Author: Vivek Yadav
Author-email: vivekkya@gmail.com
License: MIT
Download-URL: https://github.com/vivekkya/auto-release-to-pypi/archive/refs/tags/0.0.7.tar.gz
Keywords: Github Actions,PYPI,Github Release
Platform: UNKNOWN
Classifier: Development Status :: 3 - Alpha
Classifier: Intended Audience :: Developers
Classifier: Topic :: Software Development :: Build Tools
Classifier: License :: OSI Approved :: MIT License
Classifier: Programming Language :: Python :: 3
Classifier: Programming Language :: Python :: 3.5
Classifier: Programming Language :: Python :: 3.6
Classifier: Programming Language :: Python :: 3.7
License-File: LICENSE
Requires-Dist: numpy
